pyforked_daapd/__init__.py
pyforked_daapd-0.1.11.dist-info/LICENSE.txt
pyforked_daapd-0.1.11.dist-info/METADATA
pyforked_daapd-0.1.11.dist-info/WHEEL
pyforked_daapd-0.1.11.dist-info/top_level.txt
pyforked_daapd-0.1.11.dist-info/RECORD
