Metadata-Version: 2.1
Name: pyforked-daapd
Version: 0.1.11
Summary: Python Interface for forked-daapd
Home-page: http://github.com/uvjustin/pyforked-daapd/
Author: Justin Wong
Author-email: 46082645+uvjustin@users.noreply.github.com
License: UNKNOWN
Platform: any
Classifier: Programming Language :: Python
Classifier: Development Status :: 4 - Beta
Classifier: Natural Language :: English
Classifier: Environment :: Web Environment
Classifier: Intended Audience :: Developers
Classifier: License :: OSI Approved :: MIT License
Classifier: Operating System :: OS Independent
Classifier: Topic :: Software Development :: Libraries :: Python Modules
Requires-Dist: aiohttp
